{
  "queue": [
    {
      "id": "267d915a-ed10-4bef-a884-97cfcd22490a",
      "file_path": "uploads\\1004525688_20251230_061200_SOFTWARE REQUIREMENTS SPECIFICATION.pdf",
      "user_id": "1004525688",
      "chat_id": 1004525688,
      "timestamp": "2025-12-30T06:12:00.312898",
      "status": "submitted",
      "assignment": "ass01",
      "student_id": "1175430317",
      "student_name": "Student - 2 (student2@pcheckdone.com)",
      "submission_title": "5688312898b782",
      "paper_id": "",
      "similarity_score": "",
      "ai_score": "",
      "report_downloaded": false,
      "submitted_at": "2025-12-30T06:14:53.697109"
    }
  ]
}